typequery.py
typequery_tests.py
TypeQuery-0.1.5.dist-info/DESCRIPTION.rst
TypeQuery-0.1.5.dist-info/METADATA
TypeQuery-0.1.5.dist-info/RECORD
TypeQuery-0.1.5.dist-info/WHEEL
TypeQuery-0.1.5.dist-info/metadata.json
TypeQuery-0.1.5.dist-info/top_level.txt
